srswti_axis/__init__.py
srswti_axis/post_install.py
srswti_axis/classifier/README.md
srswti_axis/classifier/doc.md
srswti_axis/classifier/main.py
srswti_axis/classifier/misc.py
srswti_axis/core/README.md
srswti_axis/core/__init__.py
srswti_axis/core/base_processor.py
srswti_axis/core/doc.md
srswti_axis/core/nltk_processor.py
srswti_axis/core/spacy_processor.py
srswti_axis/core/text_cleaner.py
srswti_axis/core/toolkit.py
srswti_axis/document/README.md
srswti_axis/document/__init__.py
srswti_axis/document/base.py
srswti_axis/document/clusterer.py
srswti_axis/document/deduplicator.py
srswti_axis/document/doc.md
srswti_axis/document/graph_merge.py
srswti_axis/document/jsd.py
srswti_axis/document/jsd2.py
srswti_axis/document/merger.py
srswti_axis/document/natural_chunking.py
srswti_axis/document/ranker.py
srswti_axis/document/similarity.py
srswti_axis/document/splitter.py
srswti_axis/document/topic2.py
srswti_axis/document/topic_modeling.py
srswti_axis/llm/README.md
srswti_axis/llm/__init__.py
srswti_axis/llm/doc.md
srswti_axis/llm/main.py
srswti_axis/scientific/__init__.py
srswti_axis/scientific/citation_parser.py
srswti_axis/scientific/paper_analyzer.py
srswti_axis/scientific/scispacy_processor.py
srswti_axis/scientific/technical_extractor.py
srswti_axis/search_engines/README.md
srswti_axis/search_engines/__init__.py
srswti_axis/search_engines/bm25.py
srswti_axis/search_engines/doc.md
srswti_axis/search_engines/learn2rank.py
srswti_axis/search_engines/ranker.py
srswti_axis/search_engines/srswti_ir.log
srswti_axis/sentiment/README.md
srswti_axis/sentiment/__init__.py
srswti_axis/sentiment/doc.md
srswti_axis/sentiment/senti.py
srswti_axis/summarize/README.md
srswti_axis/summarize/__init__.py
srswti_axis/summarize/config.py
srswti_axis/summarize/doc.md
srswti_axis/summarize/main.py
srswti_axis/translation/README.md
srswti_axis/translation/__init__.py
srswti_axis/translation/doc.md
srswti_axis/translation/main.py
srswti_axis/translation/misc.py
srswti_axis-1.5.dist-info/METADATA
srswti_axis-1.5.dist-info/WHEEL
srswti_axis-1.5.dist-info/entry_points.txt
srswti_axis-1.5.dist-info/RECORD
